zzz233/__init__.py
zzz233/_internal.py
zzz233/_version.py
zzz233/data/data00.txt
zzz233/data/data01.text
zzz233-0.5.0.dist-info/licenses/LICENSES
zzz233-0.5.0.dist-info/METADATA
zzz233-0.5.0.dist-info/WHEEL
zzz233-0.5.0.dist-info/entry_points.txt
zzz233-0.5.0.dist-info/top_level.txt
zzz233-0.5.0.dist-info/RECORD
