Metadata-Version: 2.4
Name: zzz233
Version: 0.5.0
Summary: a minimalistic python package
Author-email: husisy <donot@mail.me>
License: MIT
Project-URL: Homepage, https://github.com/husisy/zzz233
Project-URL: Documentation, https://husisy.github.io/zzz233/
Keywords: toy package
Classifier: Programming Language :: Python :: 3
License-File: LICENSES
Requires-Dist: numpy
Requires-Dist: h5py
Provides-Extra: dev
Requires-Dist: twine; extra == "dev"
Requires-Dist: pytest; extra == "dev"
Requires-Dist: pytest-cov; extra == "dev"
Provides-Extra: doc
Requires-Dist: mkdocs; extra == "doc"
Requires-Dist: mkdocs-material; extra == "doc"
Requires-Dist: pymdown-extensions; extra == "doc"
Requires-Dist: mkdocstrings[python]; extra == "doc"
Dynamic: license-file
